yinhepy/YinHe.dll
yinhepy/__init__.py
yinhepy/interface.dll
yinhepy/libcurl.py
yinhepy/librist.dll
yinhepy/syse.dll
yinhepy/w32-pthreads.dll
yinhepy/yinhe.py
yinhepy/ayin/__init__.py
yinhepy/ayin/ayinhe.py
yinhepy/jsp/__init__.py
yinhepy/jsp/yinhehq.py
yinhepy-1.3.19.dist-info/METADATA
yinhepy-1.3.19.dist-info/WHEEL
yinhepy-1.3.19.dist-info/top_level.txt
yinhepy-1.3.19.dist-info/RECORD
