Metadata-Version: 2.1
Name: yinhepy
Version: 1.3.19
Summary: yinhedata.com
Home-page: UNKNOWN
Author: yinhedata.com
License: UNKNOWN
Platform: UNKNOWN
Requires-Dist: click
Requires-Dist: six
Requires-Dist: cryptography
Requires-Dist: beautifulsoup4>=4.9.1
Requires-Dist: lxml>=4.2.1
Requires-Dist: pandas>=0.25
Requires-Dist: requests>=2.22.0
Requires-Dist: pypinyin>=0.35.0
Requires-Dist: html5lib>=1.0.1
Requires-Dist: xlrd>=1.2.0
Requires-Dist: urllib3>=1.25.8
Requires-Dist: tqdm>=4.43.0
Requires-Dist: openpyxl>=3.0.3
Requires-Dist: jsonpath>=0.82
Requires-Dist: tabulate>=0.8.6
Requires-Dist: decorator>=4.4.2
Requires-Dist: py-mini-racer>=0.6.0
Requires-Dist: akshare>=1.16.9
